flux/__init__.py
flux/constants.py
flux/errors.py
flux/event.py
flux/helpers.py
flux/machine.py
flux/state.py
flux/transition.py
tests/__init__.py
tests/test_errors.py
tests/test_event.py
tests/test_helpers.py
tests/test_state.py
tests/test_state_machine.py
flux_insha-0.1.4.dist-info/AUTHORS
flux_insha-0.1.4.dist-info/LICENSE
flux_insha-0.1.4.dist-info/METADATA
flux_insha-0.1.4.dist-info/WHEEL
flux_insha-0.1.4.dist-info/top_level.txt
flux_insha-0.1.4.dist-info/RECORD
