Metadata-Version: 2.1
Name: flux-insha
Version: 0.1.4
Summary: A lightweight finite state machine
Home-page: https://github.com/insha/Flux
Author: Farhan Ahmed
Author-email: farhan@themacronaut.com
License: BSD-3-Clause
Project-URL: Code, https://github.com/insha/Flux
Project-URL: Issue tracker, https://github.com/insha/Flux/issues
Platform: any
Classifier: Programming Language :: Python :: 3
Classifier: License :: OSI Approved :: BSD License
Classifier: Operating System :: OS Independent
Requires-Python: >=3.6
